tianbot_mini_lib/__init__.py
tianbot_mini_lib-0.1.0.dist-info/WHEEL
tianbot_mini_lib-0.1.0.dist-info/METADATA
tianbot_mini_lib-0.1.0.dist-info/RECORD
